ninja_utils/__init__.py
ninja_utils-0.1.4.dist-info/licenses/LICENSE
ninja_utils-0.1.4.dist-info/METADATA
ninja_utils-0.1.4.dist-info/WHEEL
ninja_utils-0.1.4.dist-info/top_level.txt
ninja_utils-0.1.4.dist-info/RECORD
