Metadata-Version: 2.4
Name: ninja-utils
Version: 0.1.4
Summary: Python Utils
Author-email: Fabio Antonio Astore <astore.a.fabio@gmail.com>
License: MIT License
License-File: LICENSE
Dynamic: license-file
